skybert/__init__.py
skybert-0.0.1.dist-info/METADATA
skybert-0.0.1.dist-info/WHEEL
skybert-0.0.1.dist-info/RECORD
