Metadata-Version: 2.4
Name: skybert
Version: 0.0.1
Summary: A placeholder package for the future skybert project.
Author-email: Anders Haarr <haarranders@gmail.com>
License: MIT
Keywords: placeholder,skybert
Classifier: Development Status :: 1 - Planning
Classifier: License :: OSI Approved :: MIT License
Classifier: Operating System :: OS Independent
Classifier: Programming Language :: Python :: 3
Requires-Python: >=3.10
